mcp_visualization/__init__.py
mcp_visualization/claude_config.py
mcp_visualization/cli.py
mcp_visualization/database.py
mcp_visualization/install_helper.py
mcp_visualization/main.py
mcp_visualization/server.py
mcp_visualization/config/__init__.py
mcp_visualization/config/config.yaml
mcp_visualization/config/settings.py
mcp_visualization/data/__init__.py
mcp_visualization/data/customer_data.csv
mcp_visualization/data/monthly_revenue.csv
mcp_visualization/data/product_categories.csv
mcp_visualization/data/sales_data.csv
mcp_visualization/database/__init__.py
mcp_visualization/database/interface.py
mcp_visualization/database/manager.py
mcp_visualization/database/queries.py
mcp_visualization/database/sample_data.py
mcp_visualization/databricks_integration/__init__.py
mcp_visualization/databricks_integration/credentials.py
mcp_visualization/databricks_integration/manager.py
mcp_visualization/llm/__init__.py
mcp_visualization/llm/ollama_client.py
mcp_visualization/llm/prompts.py
mcp_visualization/llm/simple_fallback.py
mcp_visualization/mcp_server/__init__.py
mcp_visualization/mcp_server/handlers.py
mcp_visualization/mcp_server/server.py
mcp_visualization/mcp_server/tools.py
mcp_visualization/mcp_server/types.py
mcp_visualization/utils/__init__.py
mcp_visualization/utils/logger.py
mcp_visualization/utils/validators.py
mcp_visualization/visualization/__init__.py
mcp_visualization/visualization/chart_generator.py
mcp_visualization/visualization/chart_types.py
mcp_visualization/visualization/insights.py
mcp_visualization_duckdb-0.1.11.dist-info/licenses/LICENSE
mcp_visualization_duckdb-0.1.11.dist-info/METADATA
mcp_visualization_duckdb-0.1.11.dist-info/WHEEL
mcp_visualization_duckdb-0.1.11.dist-info/entry_points.txt
mcp_visualization_duckdb-0.1.11.dist-info/top_level.txt
mcp_visualization_duckdb-0.1.11.dist-info/RECORD
