Metadata-Version: 2.4
Name: mcp-visualization-duckdb
Version: 0.1.11
Summary: Transform natural language into beautiful data visualizations using Claude Desktop with DuckDB and Databricks support
Author: MCP Visualization Contributors
License: MIT
Project-URL: Homepage, https://github.com/your-github-username/mcp-visualization-duckdb
Project-URL: Documentation, https://github.com/your-github-username/mcp-visualization-duckdb#readme
Project-URL: Repository, https://github.com/your-github-username/mcp-visualization-duckdb.git
Project-URL: Issues, https://github.com/your-github-username/mcp-visualization-duckdb/issues
Keywords: mcp,claude,desktop,visualization,duckdb,databricks,charts,data-analysis,sql,warehouse
Classifier: Development Status :: 4 - Beta
Classifier: Intended Audience :: Developers
Classifier: Intended Audience :: Science/Research
Classifier: License :: OSI Approved :: MIT License
Classifier: Operating System :: OS Independent
Classifier: Programming Language :: Python :: 3
Classifier: Programming Language :: Python :: 3.8
Classifier: Programming Language :: Python :: 3.9
Classifier: Programming Language :: Python :: 3.10
Classifier: Programming Language :: Python :: 3.11
Classifier: Programming Language :: Python :: 3.12
Classifier: Topic :: Scientific/Engineering :: Visualization
Classifier: Topic :: Database
Classifier: Topic :: Software Development :: Libraries :: Python Modules
Requires-Python: >=3.8
License-File: LICENSE
Requires-Dist: mcp>=1.0.0
Requires-Dist: duckdb>=0.9.0
Requires-Dist: pandas>=2.0.0
Requires-Dist: plotly>=5.17.0
Requires-Dist: pydantic>=2.0.0
Requires-Dist: pydantic-settings>=2.0.0
Requires-Dist: PyYAML>=6.0
Requires-Dist: rich>=13.0.0
Requires-Dist: click>=8.1.0
Requires-Dist: httpx>=0.25.0
Requires-Dist: numpy>=1.24.0
Requires-Dist: databricks-sql-connector>=3.0.0
Requires-Dist: keyring>=24.0.0
Requires-Dist: cryptography>=41.0.0
Provides-Extra: dev
Requires-Dist: pytest>=7.4.0; extra == "dev"
Requires-Dist: pytest-asyncio>=0.21.0; extra == "dev"
Requires-Dist: pytest-cov>=4.1.0; extra == "dev"
Requires-Dist: black>=23.0.0; extra == "dev"
Requires-Dist: isort>=5.12.0; extra == "dev"
Requires-Dist: mypy>=1.5.0; extra == "dev"
Provides-Extra: advanced
Requires-Dist: kaleido>=0.2.1; extra == "advanced"
Requires-Dist: seaborn>=0.12.0; extra == "advanced"
Requires-Dist: matplotlib>=3.7.0; extra == "advanced"
Requires-Dist: sqlalchemy>=2.0.0; extra == "advanced"
Dynamic: license-file
